{"name":"build-javascript","namedChunkGroups":{"polyfill":{"name":"polyfill","assets":[{"name":"webpack-runtime-f767d377415e3e2c5a90.js","size":3914},{"name":"polyfill-3a43c187f95297164671.js","size":85836}],"filteredAssets":0,"assetsSize":89750,"filteredAuxiliaryAssets":2,"auxiliaryAssetsSize":223612},"app":{"name":"app","assets":[{"name":"webpack-runtime-f767d377415e3e2c5a90.js","size":3914},{"name":"framework-2933583651c6f9917e11.js","size":129749},{"name":"styles.d2c0e9323db1c23238ae.css","size":3622},{"name":"app-238e52ceb32c6ee08b2b.js","size":76547}],"filteredAssets":0,"assetsSize":213832,"filteredAuxiliaryAssets":3,"auxiliaryAssetsSize":674423},"component---src-pages-404-js":{"name":"component---src-pages-404-js","assets":[{"name":"component---src-pages-404-js-4022a43d5f10b5086a44.js","size":799}],"filteredAssets":0,"assetsSize":799,"filteredAuxiliaryAssets":1,"auxiliaryAssetsSize":1975},"component---src-pages-dummy-js":{"name":"component---src-pages-dummy-js","assets":[{"name":"component---src-pages-dummy-js-04ad9f3b1f1529f8bfad.js","size":1046}],"filteredAssets":0,"assetsSize":1046,"filteredAuxiliaryAssets":1,"auxiliaryAssetsSize":2012},"component---src-pages-index-js":{"name":"component---src-pages-index-js","assets":[{"name":"component---src-pages-index-js-ca4f6dc32bcf35594448.js","size":5573}],"filteredAssets":0,"assetsSize":5573,"filteredAuxiliaryAssets":1,"auxiliaryAssetsSize":13086}},"assetsByChunkName":{"polyfill":["webpack-runtime-f767d377415e3e2c5a90.js","polyfill-3a43c187f95297164671.js"],"app":["webpack-runtime-f767d377415e3e2c5a90.js","framework-2933583651c6f9917e11.js","styles.d2c0e9323db1c23238ae.css","app-238e52ceb32c6ee08b2b.js"],"component---src-pages-404-js":["component---src-pages-404-js-4022a43d5f10b5086a44.js"],"component---src-pages-dummy-js":["component---src-pages-dummy-js-04ad9f3b1f1529f8bfad.js"],"component---src-pages-index-js":["component---src-pages-index-js-ca4f6dc32bcf35594448.js"]},"childAssetsByChunkName":{}}